liteeth/__init__.py
liteeth/common.py
liteeth/crossbar.py
liteeth/gen.py
liteeth/packet.py
liteeth/core/__init__.py
liteeth/core/arp.py
liteeth/core/dhcp.py
liteeth/core/icmp.py
liteeth/core/ip.py
liteeth/core/udp.py
liteeth/frontend/__init__.py
liteeth/frontend/etherbone.py
liteeth/frontend/stream.py
liteeth/mac/__init__.py
liteeth/mac/common.py
liteeth/mac/core.py
liteeth/mac/crc.py
liteeth/mac/gap.py
liteeth/mac/last_be.py
liteeth/mac/padding.py
liteeth/mac/preamble.py
liteeth/mac/sram.py
liteeth/mac/wishbone.py
liteeth/phy/__init__.py
liteeth/phy/a7_1000basex.py
liteeth/phy/a7_gtp.py
liteeth/phy/common.py
liteeth/phy/ecp5rgmii.py
liteeth/phy/gmii.py
liteeth/phy/gmii_mii.py
liteeth/phy/gw5rgmii.py
liteeth/phy/k7_1000basex.py
liteeth/phy/ku_1000basex.py
liteeth/phy/mii.py
liteeth/phy/model.py
liteeth/phy/pcs_1000basex.py
liteeth/phy/rmii.py
liteeth/phy/s6rgmii.py
liteeth/phy/s7rgmii.py
liteeth/phy/titaniumrgmii.py
liteeth/phy/trionrgmii.py
liteeth/phy/usp_gth_1000basex.py
liteeth/phy/usp_gty_1000basex.py
liteeth/phy/usp_gty_10g_baser.py
liteeth/phy/usrgmii.py
liteeth/phy/v7_1000basex.py
liteeth/phy/xgmii.py
liteeth/software/__init__.py
liteeth/software/dissector/etherbone.lua
liteeth-2024.12.dist-info/licenses/LICENSE
liteeth-2024.12.dist-info/METADATA
liteeth-2024.12.dist-info/WHEEL
liteeth-2024.12.dist-info/entry_points.txt
liteeth-2024.12.dist-info/top_level.txt
liteeth-2024.12.dist-info/RECORD
